thonnycontrib/thonny-flake8/__init__.py
thonny_flake-1.0.3.dist-info/LICENSE
thonny_flake-1.0.3.dist-info/METADATA
thonny_flake-1.0.3.dist-info/WHEEL
thonny_flake-1.0.3.dist-info/top_level.txt
thonny_flake-1.0.3.dist-info/RECORD
