Metadata-Version: 2.1
Name: thonny-flake
Version: 1.0.3
Summary: A plugin that adds flake8 warnings to the Thonny Python IDE.
Home-page: https://github.com/bigjango13/thonny-flake8
Author: Bigjango13
License: UNKNOWN
Platform: UNKNOWN
Classifier: Programming Language :: Python :: 3
Classifier: Environment :: Plugins
Classifier: Intended Audience :: Education
Classifier: Operating System :: OS Independent
Requires-Python: >=3.7
Requires-Dist: Flake8
Requires-Dist: thonny (>=3.0.0)
